CHANGES
COPYRIGHT
MANIFEST.in
NOTICE
README
TODO
setup.cfg
setup.py
BloodhoundLabs.egg-info/PKG-INFO
BloodhoundLabs.egg-info/SOURCES.txt
BloodhoundLabs.egg-info/dependency_links.txt
BloodhoundLabs.egg-info/entry_points.txt
BloodhoundLabs.egg-info/requires.txt
BloodhoundLabs.egg-info/top_level.txt
bhlabs/__init__.py
bhlabs/attachment.py
bhlabs/hooks_routes.py
bhlabs/jquery_layout.py
bhlabs/search.py
bhlabs/theme.py
bhlabs/util.py
bhlabs/htdocs/screenshot.png
bhlabs/htdocs/css/jq.css
bhlabs/htdocs/css/layout-default.css
bhlabs/htdocs/img/D1E6FC_40x100_textures_10_dots_medium_90.png
bhlabs/htdocs/img/go-lt-off.gif
bhlabs/htdocs/img/go-lt-on.gif
bhlabs/htdocs/img/go-rt-off.gif
bhlabs/htdocs/img/go-rt-on.gif
bhlabs/htdocs/img/pin-dn-off.gif
bhlabs/htdocs/img/pin-dn-on.gif
bhlabs/htdocs/img/pin-up-off.gif
bhlabs/htdocs/img/pin-up-on.gif
bhlabs/htdocs/img/resizable-e.gif
bhlabs/htdocs/img/resizable-s.gif
bhlabs/htdocs/img/resizable-w.gif
bhlabs/htdocs/jquery.fupload/css/jquery.fileupload-ui.css
bhlabs/htdocs/jquery.fupload/js/jquery.fileupload-fp.min.js
bhlabs/htdocs/jquery.fupload/js/jquery.fileupload-ui.min.js
bhlabs/htdocs/jquery.fupload/js/jquery.fileupload.min.js
bhlabs/htdocs/jquery.fupload/js/jquery.iframe-transport.min.js
bhlabs/htdocs/jquery.fupload/js/jquery.ui.widget.min.js
bhlabs/htdocs/jquery/css/jquery.fileupload-ui.css
bhlabs/htdocs/jquery/css/base/jquery.ui.accordion.css
bhlabs/htdocs/jquery/css/base/jquery.ui.all.css
bhlabs/htdocs/jquery/css/base/jquery.ui.autocomplete.css
bhlabs/htdocs/jquery/css/base/jquery.ui.base.css
bhlabs/htdocs/jquery/css/base/jquery.ui.button.css
bhlabs/htdocs/jquery/css/base/jquery.ui.core.css
bhlabs/htdocs/jquery/css/base/jquery.ui.datepicker.css
bhlabs/htdocs/jquery/css/base/jquery.ui.dialog.css
bhlabs/htdocs/jquery/css/base/jquery.ui.progressbar.css
bhlabs/htdocs/jquery/css/base/jquery.ui.resizable.css
bhlabs/htdocs/jquery/css/base/jquery.ui.selectable.css
bhlabs/htdocs/jquery/css/base/jquery.ui.slider.css
bhlabs/htdocs/jquery/css/base/jquery.ui.tabs.css
bhlabs/htdocs/jquery/css/base/jquery.ui.theme.css
bhlabs/htdocs/jquery/css/base/images/ui-bg_flat_0_aaaaaa_40x100.png
bhlabs/htdocs/jquery/css/base/images/ui-bg_flat_75_ffffff_40x100.png
